asyncpd/__init__.py
asyncpd/client.py
asyncpd/py.typed
asyncpd/utils.py
asyncpd/version.py
asyncpd/models/__init__.py
asyncpd/models/abilities.py
asyncpd/models/addons.py
asyncpd/models/analytics.py
asyncpd/models/pagination.py
asyncpd/models/service.py
asyncpd-0.0.2.dist-info/LICENSE
asyncpd-0.0.2.dist-info/METADATA
asyncpd-0.0.2.dist-info/WHEEL
asyncpd-0.0.2.dist-info/top_level.txt
asyncpd-0.0.2.dist-info/RECORD
